<MinutiaeList>
    <Minutia X="973" Y="782" Angle="332.0" Type="E" />
    <Minutia X="1059" Y="1013" Angle="329.0" Type="E" />
    <Minutia X="1186" Y="1102" Angle="144.0" Type="E" />
    <Minutia X="1120" Y="1173" Angle="312.0" Type="E" />
    <Minutia X="1245" Y="1247" Angle="175.0" Type="E" />
    <Minutia X="1166" Y="1265" Angle="325.0" Type="E" />
    <Minutia X="1311" Y="1323" Angle="189.0" Type="E" />
    <Minutia X="1179" Y="1422" Angle="77.0" Type="B" />
    <Minutia X="1278" Y="1461" Angle="44.0" Type="E" />
    <Minutia X="1173" Y="1593" Angle="48.0" Type="E" />
    <Minutia X="1234" Y="1575" Angle="222.0" Type="E" />
    <Minutia X="1262" Y="1603" Angle="42.0" Type="B" />
    <Minutia X="1163" Y="1709" Angle="42.0" Type="E" />
    <Minutia X="1016" Y="1956" Angle="30.0" Type="E" />
    <Minutia X="1059" Y="1839" Angle="40.0" Type="E" />
    <Minutia X="1019" Y="930" Angle="328.0" Type="E" />
    <Minutia X="1049" Y="889" Angle="158.0" Type="E" />
    <Minutia X="991" Y="864" Angle="335.0" Type="E" />
    <Minutia X="1107" Y="965" Angle="152.0" Type="B" />
    <Minutia X="643" Y="676" Angle="344.0" Type="E" />
    <Minutia X="780" Y="892" Angle="324.0" Type="B" />
    <Minutia X="856" Y="1603" Angle="82.0" Type="E" />
    <Minutia X="869" Y="1468" Angle="265.0" Type="E" />
    <Minutia X="660" Y="1803" Angle="57.0" Type="B" />
    <Minutia X="554" Y="1915" Angle="42.0" Type="E" />
    <Minutia X="701" Y="1963" Angle="37.0" Type="E" />
    <Minutia X="947" Y="1852" Angle="54.0" Type="B" />
    <Minutia X="1085" Y="1745" Angle="61.0" Type="B" />
    <Minutia X="716" Y="2037" Angle="28.0" Type="E" />
    <Minutia X="810" Y="1316" Angle="267.0" Type="E" />
    <Minutia X="630" Y="1130" Angle="270.0" Type="E" />
    <Minutia X="709" Y="1171" Angle="288.0" Type="E" />
    <Minutia X="655" Y="1031" Angle="327.0" Type="E" />
</MinutiaeList>