<MinutiaeList>
    <Minutia X="1359" Y="1588" Angle="267.0" Type="E" />
    <Minutia X="1412" Y="1763" Angle="138.0" Type="B" />
    <Minutia X="1681" Y="1778" Angle="169.0" Type="B" />
    <Minutia X="1641" Y="1689" Angle="345.0" Type="B" />
    <Minutia X="1374" Y="1506" Angle="211.0" Type="B" />
    <Minutia X="1234" Y="1509" Angle="244.0" Type="B" />
    <Minutia X="1204" Y="1623" Angle="82.0" Type="B" />
    <Minutia X="1194" Y="1750" Angle="305.0" Type="B" />
    <Minutia X="1059" Y="1621" Angle="279.0" Type="E" />
    <Minutia X="1148" Y="1491" Angle="249.0" Type="B" />
    <Minutia X="1036" Y="1430" Angle="242.0" Type="B" />
</MinutiaeList>