<MinutiaeList>
    <Minutia X="942" Y="1486" Angle="198.0" Type="E" />
    <Minutia X="968" Y="1537" Angle="17.0" Type="E" />
    <Minutia X="1247" Y="1422" Angle="353.0" Type="B" />
    <Minutia X="1384" Y="1466" Angle="335.0" Type="B" />
    <Minutia X="1369" Y="1664" Angle="291.0" Type="E" />
    <Minutia X="1280" Y="1895" Angle="233.0" Type="E" />
    <Minutia X="1057" Y="2037" Angle="208.0" Type="B" />
    <Minutia X="945" Y="2012" Angle="201.0" Type="B" />
    <Minutia X="1107" Y="1887" Angle="204.0" Type="B" />
    <Minutia X="1168" Y="1715" Angle="348.0" Type="B" />
    <Minutia X="1179" Y="1694" Angle="173.0" Type="B" />
    <Minutia X="1115" Y="1847" Angle="35.0" Type="E" />
    <Minutia X="1171" Y="1783" Angle="240.0" Type="E" />
    <Minutia X="1072" Y="1748" Angle="197.0" Type="E" />
    <Minutia X="983" Y="1875" Angle="189.0" Type="B" />
    <Minutia X="1118" Y="1697" Angle="346.0" Type="E" />
    <Minutia X="1059" Y="1659" Angle="14.0" Type="B" />
    <Minutia X="1003" Y="1699" Angle="9.0" Type="E" />
    <Minutia X="1031" Y="1694" Angle="191.0" Type="E" />
    <Minutia X="874" Y="1687" Angle="19.0" Type="B" />
    <Minutia X="792" Y="1674" Angle="30.0" Type="E" />
    <Minutia X="541" Y="1445" Angle="238.0" Type="E" />
    <Minutia X="1039" Y="1242" Angle="14.0" Type="E" />
    <Minutia X="1331" Y="1176" Angle="358.0" Type="E" />
    <Minutia X="1427" Y="1179" Angle="177.0" Type="E" />
    <Minutia X="1453" Y="1189" Angle="353.0" Type="E" />
    <Minutia X="1491" Y="1196" Angle="160.0" Type="E" />
    <Minutia X="1433" Y="1069" Angle="359.0" Type="B" />
    <Minutia X="996" Y="1100" Angle="192.0" Type="E" />
    <Minutia X="1273" Y="1326" Angle="359.0" Type="B" />
    <Minutia X="1189" Y="1547" Angle="353.0" Type="E" />
    <Minutia X="968" Y="1026" Angle="9.0" Type="E" />
    <Minutia X="841" Y="1057" Angle="201.0" Type="E" />
    <Minutia X="754" Y="1115" Angle="205.0" Type="E" />
    <Minutia X="810" Y="1100" Angle="18.0" Type="E" />
    <Minutia X="734" Y="1074" Angle="19.0" Type="B" />
    <Minutia X="638" Y="1087" Angle="199.0" Type="E" />
    <Minutia X="541" Y="1222" Angle="28.0" Type="E" />
    <Minutia X="632" Y="1255" Angle="23.0" Type="E" />
</MinutiaeList>