<MinutiaeList>
    <Minutia X="947" Y="419" Angle="159.0" Type="E" />
    <Minutia X="909" Y="406" Angle="339.0" Type="E" />
    <Minutia X="1163" Y="391" Angle="146.0" Type="B" />
    <Minutia X="1199" Y="445" Angle="325.0" Type="E" />
    <Minutia X="1364" Y="709" Angle="319.0" Type="E" />
    <Minutia X="1293" Y="709" Angle="314.0" Type="E" />
    <Minutia X="1374" Y="914" Angle="310.0" Type="B" />
    <Minutia X="1118" Y="681" Angle="319.0" Type="E" />
    <Minutia X="1189" Y="737" Angle="142.0" Type="E" />
    <Minutia X="914" Y="1219" Angle="290.0" Type="E" />
    <Minutia X="892" Y="1085" Angle="352.0" Type="B" />
    <Minutia X="866" Y="942" Angle="187.0" Type="B" />
    <Minutia X="800" Y="917" Angle="14.0" Type="B" />
    <Minutia X="701" Y="958" Angle="224.0" Type="E" />
    <Minutia X="582" Y="965" Angle="234.0" Type="E" />
    <Minutia X="564" Y="899" Angle="41.0" Type="E" />
    <Minutia X="485" Y="1001" Angle="250.0" Type="E" />
    <Minutia X="660" Y="1283" Angle="268.0" Type="E" />
    <Minutia X="500" Y="1237" Angle="272.0" Type="E" />
    <Minutia X="508" Y="1168" Angle="82.0" Type="E" />
    <Minutia X="523" Y="1471" Angle="280.0" Type="E" />
    <Minutia X="511" Y="1430" Angle="98.0" Type="E" />
    <Minutia X="843" Y="1067" Angle="39.0" Type="E" />
    <Minutia X="879" Y="1049" Angle="207.0" Type="E" />
    <Minutia X="1024" Y="1130" Angle="137.0" Type="E" />
    <Minutia X="1151" Y="1143" Angle="304.0" Type="E" />
    <Minutia X="1255" Y="1394" Angle="108.0" Type="E" />
    <Minutia X="1389" Y="1196" Angle="295.0" Type="E" />
    <Minutia X="1168" Y="1488" Angle="134.0" Type="E" />
    <Minutia X="955" Y="704" Angle="169.0" Type="E" />
    <Minutia X="1107" Y="864" Angle="145.0" Type="E" />
    <Minutia X="914" Y="914" Angle="345.0" Type="E" />
    <Minutia X="1001" Y="958" Angle="151.0" Type="E" />
    <Minutia X="775" Y="1491" Angle="306.0" Type="E" />
    <Minutia X="663" Y="1654" Angle="121.0" Type="B" />
    <Minutia X="871" Y="1468" Angle="307.0" Type="B" />
</MinutiaeList>