<MinutiaeList>
    <Minutia X="767" Y="846" Angle="24.0" Type="B" />
    <Minutia X="719" Y="726" Angle="28.0" Type="E" />
    <Minutia X="417" Y="671" Angle="55.0" Type="E" />
    <Minutia X="318" Y="648" Angle="55.0" Type="E" />
    <Minutia X="371" Y="1128" Angle="249.0" Type="B" />
    <Minutia X="531" Y="1067" Angle="67.0" Type="E" />
    <Minutia X="853" Y="968" Angle="340.0" Type="E" />
    <Minutia X="838" Y="1072" Angle="261.0" Type="E" />
    <Minutia X="838" Y="1163" Angle="260.0" Type="B" />
    <Minutia X="907" Y="1306" Angle="253.0" Type="E" />
    <Minutia X="1003" Y="1300" Angle="263.0" Type="E" />
    <Minutia X="1064" Y="1494" Angle="76.0" Type="E" />
</MinutiaeList>