<MinutiaeList>
    <Minutia X="770" Y="635" Angle="289.0" Type="B" />
    <Minutia X="820" Y="658" Angle="302.0" Type="E" />
    <Minutia X="851" Y="699" Angle="124.0" Type="E" />
    <Minutia X="876" Y="706" Angle="97.0" Type="E" />
    <Minutia X="704" Y="610" Angle="81.0" Type="E" />
    <Minutia X="714" Y="569" Angle="243.0" Type="E" />
    <Minutia X="467" Y="607" Angle="272.0" Type="E" />
    <Minutia X="518" Y="569" Angle="88.0" Type="E" />
    <Minutia X="495" Y="777" Angle="279.0" Type="E" />
    <Minutia X="488" Y="970" Angle="287.0" Type="E" />
    <Minutia X="462" Y="1044" Angle="283.0" Type="E" />
    <Minutia X="688" Y="1613" Angle="160.0" Type="E" />
    <Minutia X="932" Y="1664" Angle="173.0" Type="E" />
</MinutiaeList>