<MinutiaeList>
    <Minutia X="988" Y="1425" Angle="304.0" Type="E" />
    <Minutia X="869" Y="1229" Angle="298.0" Type="E" />
    <Minutia X="861" Y="1090" Angle="302.0" Type="E" />
    <Minutia X="749" Y="709" Angle="335.0" Type="E" />
    <Minutia X="1588" Y="884" Angle="195.0" Type="E" />
    <Minutia X="1448" Y="686" Angle="176.0" Type="E" />
    <Minutia X="704" Y="1737" Angle="119.0" Type="B" />
    <Minutia X="1308" Y="1433" Angle="211.0" Type="E" />
    <Minutia X="805" Y="902" Angle="330.0" Type="E" />
    <Minutia X="945" Y="1069" Angle="312.0" Type="B" />
    <Minutia X="864" Y="853" Angle="327.0" Type="E" />
</MinutiaeList>