<MinutiaeList>
    <Minutia X="1182" Y="1281" Angle="171.0" Type="E" />
    <Minutia X="966" Y="1248" Angle="336.0" Type="E" />
    <Minutia X="981" Y="1204" Angle="156.0" Type="E" />
    <Minutia X="950" Y="1095" Angle="337.0" Type="E" />
    <Minutia X="1044" Y="922" Angle="358.0" Type="E" />
    <Minutia X="740" Y="922" Angle="168.0" Type="E" />
    <Minutia X="425" Y="887" Angle="162.0" Type="B" />
    <Minutia X="387" Y="470" Angle="315.0" Type="E" />
    <Minutia X="1291" Y="1176" Angle="170.0" Type="E" />
    <Minutia X="1174" Y="1215" Angle="345.0" Type="E" />
</MinutiaeList>