<MinutiaeList>
    <Minutia X="1575" Y="1087" Angle="205.0" Type="B" />
    <Minutia X="1532" Y="1148" Angle="54.0" Type="E" />
    <Minutia X="1557" Y="1171" Angle="302.0" Type="B" />
    <Minutia X="1588" Y="1156" Angle="315.0" Type="B" />
    <Minutia X="1786" Y="1306" Angle="323.0" Type="B" />
    <Minutia X="1943" Y="1351" Angle="158.0" Type="B" />
    <Minutia X="1814" Y="1255" Angle="333.0" Type="B" />
    <Minutia X="1633" Y="904" Angle="157.0" Type="B" />
    <Minutia X="1402" Y="859" Angle="18.0" Type="B" />
    <Minutia X="1435" Y="813" Angle="191.0" Type="B" />
    <Minutia X="1392" Y="569" Angle="358.0" Type="E" />
    <Minutia X="1394" Y="498" Angle="192.0" Type="E" />
    <Minutia X="2101" Y="754" Angle="345.0" Type="E" />
    <Minutia X="2306" Y="808" Angle="162.0" Type="B" />
    <Minutia X="1905" Y="663" Angle="318.0" Type="E" />
    <Minutia X="1867" Y="660" Angle="149.0" Type="E" />
    <Minutia X="1963" Y="643" Angle="324.0" Type="E" />
    <Minutia X="1935" Y="648" Angle="151.0" Type="E" />
    <Minutia X="1900" Y="348" Angle="146.0" Type="E" />
    <Minutia X="1278" Y="267" Angle="10.0" Type="E" />
    <Minutia X="1641" Y="241" Angle="336.0" Type="E" />
    <Minutia X="2438" Y="495" Angle="345.0" Type="E" />
</MinutiaeList>