<MinutiaeList>
    <Minutia X="1445" Y="653" Angle="85.0" Type="B" />
    <Minutia X="1461" Y="716" Angle="260.0" Type="E" />
    <Minutia X="1638" Y="810" Angle="252.0" Type="E" />
    <Minutia X="917" Y="711" Angle="235.0" Type="E" />
    <Minutia X="790" Y="683" Angle="241.0" Type="E" />
    <Minutia X="767" Y="554" Angle="216.0" Type="E" />
    <Minutia X="968" Y="650" Angle="200.0" Type="E" />
    <Minutia X="1013" Y="660" Angle="263.0" Type="E" />
    <Minutia X="701" Y="879" Angle="74.0" Type="E" />
    <Minutia X="1024" Y="584" Angle="247.0" Type="E" />
    <Minutia X="1036" Y="594" Angle="288.0" Type="E" />
    <Minutia X="1003" Y="582" Angle="201.0" Type="E" />
    <Minutia X="838" Y="912" Angle="70.0" Type="B" />
</MinutiaeList>