<MinutiaeList>
    <Minutia X="1372" Y="1781" Angle="232.0" Type="B" />
    <Minutia X="1486" Y="1430" Angle="268.0" Type="E" />
    <Minutia X="1463" Y="1415" Angle="260.0" Type="E" />
    <Minutia X="1420" Y="1417" Angle="245.0" Type="E" />
    <Minutia X="1417" Y="1397" Angle="204.0" Type="E" />
    <Minutia X="1311" Y="1433" Angle="224.0" Type="E" />
    <Minutia X="1554" Y="1415" Angle="288.0" Type="E" />
    <Minutia X="1656" Y="1532" Angle="268.0" Type="E" />
    <Minutia X="1857" Y="1588" Angle="270.0" Type="E" />
    <Minutia X="1839" Y="1671" Angle="74.0" Type="E" />
    <Minutia X="1778" Y="1816" Angle="46.0" Type="B" />
    <Minutia X="1875" Y="1516" Angle="310.0" Type="B" />
    <Minutia X="1775" Y="1400" Angle="307.0" Type="E" />
    <Minutia X="1664" Y="1275" Angle="312.0" Type="B" />
    <Minutia X="1631" Y="1214" Angle="146.0" Type="E" />
    <Minutia X="1814" Y="1288" Angle="315.0" Type="E" />
    <Minutia X="1834" Y="1306" Angle="149.0" Type="E" />
    <Minutia X="1996" Y="1278" Angle="324.0" Type="E" />
    <Minutia X="1854" Y="2009" Angle="27.0" Type="E" />
    <Minutia X="1798" Y="2210" Angle="20.0" Type="E" />
    <Minutia X="1534" Y="1796" Angle="60.0" Type="B" />
    <Minutia X="1506" Y="1742" Angle="241.0" Type="E" />
    <Minutia X="1361" Y="1913" Angle="49.0" Type="B" />
    <Minutia X="2062" Y="1542" Angle="162.0" Type="E" />
    <Minutia X="1814" Y="2261" Angle="201.0" Type="E" />
    <Minutia X="1588" Y="2319" Angle="33.0" Type="E" />
    <Minutia X="1295" Y="2400" Angle="24.0" Type="B" />
    <Minutia X="1615" Y="2111" Angle="32.0" Type="E" />
    <Minutia X="1659" Y="2393" Angle="17.0" Type="E" />
    <Minutia X="1869" Y="1801" Angle="35.0" Type="E" />
    <Minutia X="1605" Y="1948" Angle="43.0" Type="E" />
    <Minutia X="1590" Y="2027" Angle="38.0" Type="B" />
    <Minutia X="1367" Y="2103" Angle="42.0" Type="B" />
    <Minutia X="1481" Y="1318" Angle="160.0" Type="B" />
    <Minutia X="1331" Y="1199" Angle="6.0" Type="E" />
    <Minutia X="1107" Y="1364" Angle="224.0" Type="E" />
    <Minutia X="950" Y="2487" Angle="185.0" Type="E" />
    <Minutia X="2377" Y="1420" Angle="161.0" Type="B" />
    <Minutia X="1773" Y="1039" Angle="322.0" Type="E" />
    <Minutia X="2296" Y="1331" Angle="344.0" Type="E" />
    <Minutia X="1839" Y="2332" Angle="194.0" Type="E" />
    <Minutia X="1953" Y="1641" Angle="184.0" Type="E" />
    <Minutia X="1770" Y="927" Angle="325.0" Type="E" />
    <Minutia X="2113" Y="1029" Angle="336.0" Type="E" />
</MinutiaeList>