<MinutiaeList>
    <Minutia X="1102" Y="1306" Angle="153.0" Type="B" />
    <Minutia X="960" Y="1336" Angle="32.0" Type="E" />
    <Minutia X="1209" Y="1351" Angle="289.0" Type="E" />
    <Minutia X="1189" Y="1252" Angle="302.0" Type="B" />
    <Minutia X="1196" Y="1151" Angle="323.0" Type="B" />
    <Minutia X="1113" Y="1008" Angle="183.0" Type="E" />
    <Minutia X="1082" Y="828" Angle="353.0" Type="E" />
    <Minutia X="1207" Y="815" Angle="170.0" Type="E" />
    <Minutia X="1196" Y="734" Angle="347.0" Type="E" />
    <Minutia X="1323" Y="749" Angle="161.0" Type="B" />
    <Minutia X="1054" Y="754" Angle="183.0" Type="E" />
    <Minutia X="800" Y="848" Angle="33.0" Type="E" />
    <Minutia X="762" Y="495" Angle="30.0" Type="B" />
    <Minutia X="919" Y="480" Angle="200.0" Type="E" />
    <Minutia X="533" Y="739" Angle="40.0" Type="E" />
    <Minutia X="488" Y="859" Angle="219.0" Type="B" />
    <Minutia X="1036" Y="1359" Angle="320.0" Type="E" />
    <Minutia X="1087" Y="1425" Angle="111.0" Type="E" />
    <Minutia X="1087" Y="1588" Angle="248.0" Type="E" />
    <Minutia X="991" Y="305" Angle="191.0" Type="B" />
    <Minutia X="300" Y="1024" Angle="36.0" Type="E" />
    <Minutia X="716" Y="988" Angle="42.0" Type="E" />
    <Minutia X="622" Y="1308" Angle="46.0" Type="E" />
    <Minutia X="1107" Y="1064" Angle="7.0" Type="E" />
    <Minutia X="998" Y="1496" Angle="250.0" Type="E" />
    <Minutia X="1046" Y="1448" Angle="285.0" Type="E" />
</MinutiaeList>