<MinutiaeList>
    <Minutia X="699" Y="765" Angle="16.0" Type="B" />
    <Minutia X="1166" Y="821" Angle="3.0" Type="E" />
    <Minutia X="1296" Y="780" Angle="184.0" Type="E" />
    <Minutia X="740" Y="856" Angle="206.0" Type="E" />
    <Minutia X="1060" Y="897" Angle="192.0" Type="E" />
    <Minutia X="1436" Y="1027" Angle="154.0" Type="B" />
    <Minutia X="1174" Y="986" Angle="358.0" Type="E" />
    <Minutia X="902" Y="976" Angle="13.0" Type="E" />
    <Minutia X="1027" Y="1052" Angle="201.0" Type="E" />
    <Minutia X="557" Y="1273" Angle="226.0" Type="E" />
    <Minutia X="668" Y="1253" Angle="40.0" Type="E" />
    <Minutia X="577" Y="1456" Angle="43.0" Type="E" />
    <Minutia X="829" Y="1491" Angle="49.0" Type="E" />
    <Minutia X="765" Y="1667" Angle="38.0" Type="B" />
    <Minutia X="963" Y="1517" Angle="38.0" Type="E" />
    <Minutia X="1001" Y="1489" Angle="216.0" Type="E" />
    <Minutia X="1034" Y="1479" Angle="17.0" Type="E" />
    <Minutia X="1062" Y="1466" Angle="197.0" Type="E" />
    <Minutia X="1075" Y="1552" Angle="196.0" Type="E" />
    <Minutia X="1108" Y="1644" Angle="185.0" Type="E" />
    <Minutia X="1215" Y="1725" Angle="132.0" Type="E" />
    <Minutia X="1027" Y="1814" Angle="228.0" Type="E" />
    <Minutia X="945" Y="1959" Angle="51.0" Type="E" />
    <Minutia X="686" Y="2032" Angle="29.0" Type="E" />
    <Minutia X="488" Y="2106" Angle="26.0" Type="E" />
    <Minutia X="526" Y="1954" Angle="38.0" Type="E" />
    <Minutia X="808" Y="2132" Angle="12.0" Type="E" />
    <Minutia X="1156" Y="2083" Angle="150.0" Type="E" />
    <Minutia X="1057" Y="1893" Angle="268.0" Type="B" />
    <Minutia X="1110" Y="1837" Angle="297.0" Type="E" />
    <Minutia X="1225" Y="2048" Angle="148.0" Type="E" />
    <Minutia X="912" Y="2076" Angle="14.0" Type="E" />
    <Minutia X="1476" Y="1563" Angle="116.0" Type="E" />
    <Minutia X="1093" Y="1799" Angle="225.0" Type="B" />
    <Minutia X="996" Y="1987" Angle="0.0" Type="E" />
    <Minutia X="1027" Y="1987" Angle="162.0" Type="E" />
    <Minutia X="676" Y="2236" Angle="13.0" Type="E" />
    <Minutia X="1108" Y="2218" Angle="167.0" Type="B" />
</MinutiaeList>