<MinutiaeList>
    <Minutia X="704" Y="737" Angle="243.0" Type="E" />
    <Minutia X="541" Y="767" Angle="65.0" Type="E" />
    <Minutia X="737" Y="551" Angle="239.0" Type="B" />
    <Minutia X="673" Y="853" Angle="75.0" Type="B" />
    <Minutia X="1953" Y="1334" Angle="292.0" Type="B" />
    <Minutia X="2101" Y="1753" Angle="276.0" Type="B" />
    <Minutia X="2162" Y="1661" Angle="105.0" Type="E" />
    <Minutia X="1471" Y="866" Angle="266.0" Type="E" />
    <Minutia X="2309" Y="1816" Angle="97.0" Type="E" />
    <Minutia X="2146" Y="1214" Angle="107.0" Type="B" />
    <Minutia X="1702" Y="1588" Angle="104.0" Type="B" />
    <Minutia X="1768" Y="1844" Angle="99.0" Type="E" />
    <Minutia X="1661" Y="1877" Angle="280.0" Type="E" />
    <Minutia X="1715" Y="1438" Angle="283.0" Type="B" />
    <Minutia X="1900" Y="1471" Angle="110.0" Type="E" />
    <Minutia X="2228" Y="2169" Angle="62.0" Type="B" />
</MinutiaeList>