<MinutiaeList>
    <Minutia X="1161" Y="709" Angle="321.0" Type="E" />
    <Minutia X="1118" Y="749" Angle="150.0" Type="E" />
    <Minutia X="1059" Y="658" Angle="342.0" Type="E" />
    <Minutia X="1087" Y="668" Angle="153.0" Type="E" />
    <Minutia X="1290" Y="1013" Angle="102.0" Type="E" />
    <Minutia X="1262" Y="1250" Angle="71.0" Type="E" />
    <Minutia X="1046" Y="1506" Angle="225.0" Type="B" />
    <Minutia X="1118" Y="1191" Angle="81.0" Type="E" />
    <Minutia X="1054" Y="714" Angle="337.0" Type="E" />
    <Minutia X="1158" Y="1384" Angle="65.0" Type="B" />
    <Minutia X="1306" Y="815" Angle="297.0" Type="E" />
    <Minutia X="1306" Y="699" Angle="323.0" Type="E" />
    <Minutia X="1331" Y="724" Angle="137.0" Type="E" />
</MinutiaeList>