<MinutiaeList>
    <Minutia X="724" Y="282" Angle="76.0" Type="E" />
    <Minutia X="765" Y="307" Angle="262.0" Type="E" />
    <Minutia X="572" Y="353" Angle="70.0" Type="E" />
    <Minutia X="643" Y="229" Angle="255.0" Type="E" />
    <Minutia X="503" Y="732" Angle="270.0" Type="E" />
    <Minutia X="505" Y="780" Angle="97.0" Type="E" />
    <Minutia X="546" Y="544" Angle="257.0" Type="E" />
    <Minutia X="541" Y="572" Angle="84.0" Type="E" />
    <Minutia X="810" Y="942" Angle="145.0" Type="E" />
    <Minutia X="1199" Y="899" Angle="314.0" Type="E" />
    <Minutia X="1110" Y="653" Angle="292.0" Type="E" />
    <Minutia X="1092" Y="610" Angle="103.0" Type="E" />
    <Minutia X="1006" Y="744" Angle="296.0" Type="E" />
    <Minutia X="1168" Y="556" Angle="297.0" Type="E" />
    <Minutia X="1864" Y="1186" Angle="96.0" Type="E" />
    <Minutia X="1623" Y="1001" Angle="329.0" Type="B" />
    <Minutia X="1704" Y="1011" Angle="338.0" Type="B" />
    <Minutia X="1740" Y="851" Angle="21.0" Type="E" />
    <Minutia X="1755" Y="930" Angle="0.0" Type="B" />
</MinutiaeList>